apocrypha/__init__.py
apocrypha/client.py
apocrypha/database.py
apocrypha/datum.py
apocrypha/exceptions.py
apocrypha/network.py
apocrypha/node.py
apocrypha/server.py
apocrypha-2.2.0.dist-info/LICENSE
apocrypha-2.2.0.dist-info/METADATA
apocrypha-2.2.0.dist-info/WHEEL
apocrypha-2.2.0.dist-info/top_level.txt
apocrypha-2.2.0.dist-info/RECORD
