Metadata-Version: 2.1
Name: apocrypha
Version: 2.2.0
Summary: A lightweight, flexible JSON server and client
Home-page: https://github.com/Gandalf-/apocrypha
Author: Austin Voecks
Author-email: austin@anardil.net
License: UNKNOWN
Download-URL: https://github.com/Gandalf-/apocrypha/archive/2.2.0tar.gz
Keywords: database,json
Platform: UNKNOWN
Classifier: Development Status :: 4 - Beta
Classifier: Programming Language :: Python :: 3
